odoo10_addon_hr_holidays_settings-10.0.1.1.0-py2.7-nspkg.pth
odoo/addons/hr_holidays_settings/README.rst
odoo/addons/hr_holidays_settings/__init__.py
odoo/addons/hr_holidays_settings/__manifest__.py
odoo/addons/hr_holidays_settings/models/__init__.py
odoo/addons/hr_holidays_settings/models/hr_holidays_config_settings.py
odoo/addons/hr_holidays_settings/static/description/icon.png
odoo/addons/hr_holidays_settings/views/hr_holidays_config_settings.xml
odoo10_addon_hr_holidays_settings-10.0.1.1.0.dist-info/DESCRIPTION.rst
odoo10_addon_hr_holidays_settings-10.0.1.1.0.dist-info/METADATA
odoo10_addon_hr_holidays_settings-10.0.1.1.0.dist-info/RECORD
odoo10_addon_hr_holidays_settings-10.0.1.1.0.dist-info/WHEEL
odoo10_addon_hr_holidays_settings-10.0.1.1.0.dist-info/metadata.json
odoo10_addon_hr_holidays_settings-10.0.1.1.0.dist-info/namespace_packages.txt
odoo10_addon_hr_holidays_settings-10.0.1.1.0.dist-info/top_level.txt
